goto.py
goto_statement-1.2.dist-info/LICENSE
goto_statement-1.2.dist-info/METADATA
goto_statement-1.2.dist-info/WHEEL
goto_statement-1.2.dist-info/top_level.txt
goto_statement-1.2.dist-info/RECORD
